{"author":{"username":{},"name":{},"organization":{},"email":{}},"objects":{"time":{"start":"0.0","stop":"29.0","change":"1.0","fps":"25.0"},"GraphWindow":{"xmin":"0.0","xmax":"50.0","ymin":"-90.0","ymax":"90.0","xgrid":"2.0","ygrid":"5.0"},"window":{"xmin":"-1.0","xmax":"9.0","ymin":"-1.0","ymax":"9.0","xgrid":"1.0","ygrid":"1.0","xunit":"meters","yunit":"meters","showAllDataAvailable":"false","drawGridNumbers":"true"},"description":{"text":"The dispersion of white light by an equilateral prism made of crown glass is modeled. The index of refraction ranges from 1.513 for red light to 1.532 for violet light.  Playing the animation will decrease the angle of incidence in 1 degree increments. (The colored rays emerging from the prism represent broader bands of color that would appear in an actual situation. That is, the spread of colors from red to blue would be along a continuum rather in discrete lines.)\n\nFor any particular angle of incidence, determine the angular spread between the emerging red and violet rays, assuming the indices of refraction given above."},"input":[{"name":"angle","text":"Initial angle of incidence","initialValue":"60.0","units":"deg","hidden":"1"},{"name":"ai","text":"Angle increment","initialValue":"1.0","units":"deg","hidden":"1"},{"name":"n","text":"Index of refraction (min)","initialValue":"1.513","units":{},"hidden":"1"},{"name":"ni","text":"Index of refraction increment","initialValue":"0.0038","units":{},"hidden":"1"},{"name":"h","text":"Prism height","initialValue":"4.0","units":{},"hidden":"1"},{"name":"v","text":"Vertex angle","initialValue":"60.0","units":"deg","hidden":"1"}],"output":[{"name":"var","text":"Vertex angle","units":"rad","calculator":{"@attributes":{"type":"parametric"},"value":"toRadians(v)"},"hidden":"1"},{"name":"i","text":"Angle of incidence","units":"deg","calculator":{"@attributes":{"type":"parametric"},"value":"angle-ai*t"}},{"name":"irad","text":"Angle of incidence","units":"rad","calculator":{"@attributes":{"type":"parametric"},"value":"toRadians(angle-ai*t)"},"hidden":"1"},{"name":"d","text":"Length of ray in prism","units":{},"calculator":{"@attributes":{"type":"parametric"},"value":"(h\/2)*sin(var)\/sin(1.57+asin(sin(irad)\/n)-var)"},"hidden":"1"},{"name":"n2","text":"n2","units":{},"calculator":{"@attributes":{"type":"parametric"},"value":"n+ni"},"hidden":"1"},{"name":"n3","text":"n3","units":{},"calculator":{"@attributes":{"type":"parametric"},"value":"n+2*ni"},"hidden":"1"},{"name":"n4","text":"n4","units":{},"calculator":{"@attributes":{"type":"parametric"},"value":"n+3*ni"},"hidden":"1"},{"name":"n5","text":"n5","units":{},"calculator":{"@attributes":{"type":"parametric"},"value":"n+4*ni"},"hidden":"1"},{"name":"n6","text":"n6","units":{},"calculator":{"@attributes":{"type":"parametric"},"value":"n+5*ni"},"hidden":"1"},{"name":"rred","text":"Angle of ref. (red)","units":"deg","calculator":{"@attributes":{"type":"parametric"},"value":"toDegrees(asin(n*sin(var-asin(sin(irad)\/n))))"},"hidden":"1"},{"name":"rviol","text":"Angle of ref. (viol)","units":"deg","calculator":{"@attributes":{"type":"parametric"},"value":"toDegrees(asin(n6*sin(var-asin(sin(irad)\/n6))))"},"hidden":"1"}],"solid":[{"name":"background","shape":{"@attributes":{"type":"rectangle","drawTrails":"false","drawVectors":"false"},"vectors":{"@attributes":{"yAccel":"false","Vel":"false","xAccel":"false","yVel":"false","xVel":"false","Accel":"false"}},"width":{"calculator":{"@attributes":{"type":"parametric"},"value":"10"}},"height":{"calculator":{"@attributes":{"type":"parametric"},"value":"10"}},"angle":{"calculator":{"@attributes":{"type":"parametric"},"value":"0"}},"graphOptions":{"@attributes":{"graphVisible":"false"},"initiallyOn":{"@attributes":{"yAccel":"false","yVel":"false","xAccel":"false","xVel":"false","yPos":"false","xPos":"false"}}}},"color":{"red":"0","green":"0","blue":"0"},"xpath":{"calculator":{"@attributes":{"type":"parametric"},"value":"4"}},"ypath":{"calculator":{"@attributes":{"type":"parametric"},"value":"4"}}},{"name":"prism","shape":{"@attributes":{"type":"polygon","drawTrails":"false","drawVectors":"false"},"points":{"point":[{"@attributes":{"index":"0"},"xpath":{"calculator":{"@attributes":{"type":"parametric"},"value":"0"}},"ypath":{"calculator":{"@attributes":{"type":"parametric"},"value":"0"}}},{"@attributes":{"index":"1"},"xpath":{"calculator":{"@attributes":{"type":"parametric"},"value":"0"}},"ypath":{"calculator":{"@attributes":{"type":"parametric"},"value":"h"}}},{"@attributes":{"index":"2"},"xpath":{"calculator":{"@attributes":{"type":"parametric"},"value":"h*cos(toRadians(30))"}},"ypath":{"calculator":{"@attributes":{"type":"parametric"},"value":"h*sin(toRadians(30))"}}}]},"vectors":{"@attributes":{"yAccel":"false","Vel":"false","xAccel":"false","yVel":"false","xVel":"false","Accel":"false"}},"width":{"calculator":{"@attributes":{"type":"parametric"},"value":"1"}},"height":{"calculator":{"@attributes":{"type":"parametric"},"value":"1"}},"graphOptions":{"@attributes":{"graphVisible":"false"},"initiallyOn":{"@attributes":{"yAccel":"false","yVel":"false","xAccel":"false","xVel":"false","yPos":"false","xPos":"false"}}}},"color":{"red":"255","green":"255","blue":"255"},"xpath":{"calculator":{"@attributes":{"type":"parametric"},"value":"0"}},"ypath":{"calculator":{"@attributes":{"type":"parametric"},"value":"0"}}},{"name":"incidentray","shape":{"@attributes":{"type":"line","drawTrails":"false","drawVectors":"false"},"vectors":{"@attributes":{"yAccel":"false","Vel":"false","xAccel":"false","yVel":"false","xVel":"false","Accel":"false"}},"width":{"calculator":{"@attributes":{"type":"parametric"},"value":"-2*cos(irad)"}},"height":{"calculator":{"@attributes":{"type":"parametric"},"value":"-2*sin(irad)"}},"angle":{"calculator":{"@attributes":{"type":"parametric"},"value":"0"}},"graphOptions":{"@attributes":{"graphVisible":"false"},"initiallyOn":{"@attributes":{"yAccel":"false","yVel":"false","xAccel":"false","xVel":"false","yPos":"false","xPos":"false"}}}},"color":{"red":"255","green":"255","blue":"255"},"xpath":{"calculator":{"@attributes":{"type":"parametric"},"value":"0"}},"ypath":{"calculator":{"@attributes":{"type":"parametric"},"value":"h\/2"}}},{"name":"refraya1","shape":{"@attributes":{"type":"line","drawTrails":"false","drawVectors":"false"},"vectors":{"@attributes":{"yAccel":"false","Vel":"false","xAccel":"false","yVel":"false","xVel":"false","Accel":"false"}},"width":{"calculator":{"@attributes":{"type":"parametric"},"value":"d*cos(asin(irad\/n))"}},"height":{"calculator":{"@attributes":{"type":"parametric"},"value":"d*sin(asin(irad\/n))"}},"angle":{"calculator":{"@attributes":{"type":"parametric"},"value":"0"}},"graphOptions":{"@attributes":{"graphVisible":"false"},"initiallyOn":{"@attributes":{"yAccel":"false","yVel":"false","xAccel":"false","xVel":"false","yPos":"false","xPos":"false"}}}},"color":{"red":"255","green":"0","blue":"0"},"xpath":{"calculator":{"@attributes":{"type":"parametric"},"value":"0"}},"ypath":{"calculator":{"@attributes":{"type":"parametric"},"value":"h\/2"}}},{"name":"refrayb1","shape":{"@attributes":{"type":"line","drawTrails":"false","drawVectors":"false"},"vectors":{"@attributes":{"yAccel":"false","Vel":"false","xAccel":"false","yVel":"false","xVel":"false","Accel":"false"}},"width":{"calculator":{"@attributes":{"type":"parametric"},"value":"9*cos(var-asin(n*sin(var-asin(sin(irad)\/n))))"}},"height":{"calculator":{"@attributes":{"type":"parametric"},"value":"9*sin(var-asin(n*sin(var-asin(sin(irad)\/n))))"}},"angle":{"calculator":{"@attributes":{"type":"parametric"},"value":"0"}},"graphOptions":{"@attributes":{"graphVisible":"false"},"initiallyOn":{"@attributes":{"yAccel":"false","yVel":"false","xAccel":"false","xVel":"false","yPos":"false","xPos":"false"}}}},"color":{"red":"255","green":"0","blue":"0"},"xpath":{"calculator":{"@attributes":{"type":"parametric"},"value":"d*cos(asin(irad\/n))"}},"ypath":{"calculator":{"@attributes":{"type":"parametric"},"value":"d*sin(asin(irad\/n))+h\/2"}}},{"name":"refraya2","shape":{"@attributes":{"type":"line","drawTrails":"false","drawVectors":"false"},"vectors":{"@attributes":{"yAccel":"false","Vel":"false","xAccel":"false","yVel":"false","xVel":"false","Accel":"false"}},"width":{"calculator":{"@attributes":{"type":"parametric"},"value":"d*cos(asin(irad\/n2))"}},"height":{"calculator":{"@attributes":{"type":"parametric"},"value":"d*sin(asin(irad\/n2))"}},"angle":{"calculator":{"@attributes":{"type":"parametric"},"value":"0"}},"graphOptions":{"@attributes":{"graphVisible":"false"},"initiallyOn":{"@attributes":{"yAccel":"false","yVel":"false","xAccel":"false","xVel":"false","yPos":"false","xPos":"false"}}}},"color":{"red":"255","green":"153","blue":"0"},"xpath":{"calculator":{"@attributes":{"type":"parametric"},"value":"0"}},"ypath":{"calculator":{"@attributes":{"type":"parametric"},"value":"h\/2"}}},{"name":"refrayb2","shape":{"@attributes":{"type":"line","drawTrails":"false","drawVectors":"false"},"vectors":{"@attributes":{"yAccel":"false","Vel":"false","xAccel":"false","yVel":"false","xVel":"false","Accel":"false"}},"width":{"calculator":{"@attributes":{"type":"parametric"},"value":"9*cos(var-asin(n2*sin(var-asin(sin(irad)\/n2))))"}},"height":{"calculator":{"@attributes":{"type":"parametric"},"value":"9*sin(var-asin(n2*sin(var-asin(sin(irad)\/n2))))"}},"angle":{"calculator":{"@attributes":{"type":"parametric"},"value":"0"}},"graphOptions":{"@attributes":{"graphVisible":"false"},"initiallyOn":{"@attributes":{"yAccel":"false","yVel":"false","xAccel":"false","xVel":"false","yPos":"false","xPos":"false"}}}},"color":{"red":"255","green":"153","blue":"0"},"xpath":{"calculator":{"@attributes":{"type":"parametric"},"value":"d*cos(asin(irad\/n2))"}},"ypath":{"calculator":{"@attributes":{"type":"parametric"},"value":"d*sin(asin(irad\/n2))+h\/2"}}},{"name":"refraya3","shape":{"@attributes":{"type":"line","drawTrails":"false","drawVectors":"false"},"vectors":{"@attributes":{"yAccel":"false","Vel":"false","xAccel":"false","yVel":"false","xVel":"false","Accel":"false"}},"width":{"calculator":{"@attributes":{"type":"parametric"},"value":"d*cos(asin(irad\/n3))"}},"height":{"calculator":{"@attributes":{"type":"parametric"},"value":"d*sin(asin(irad\/n3))"}},"angle":{"calculator":{"@attributes":{"type":"parametric"},"value":"0"}},"graphOptions":{"@attributes":{"graphVisible":"false"},"initiallyOn":{"@attributes":{"yAccel":"false","yVel":"false","xAccel":"false","xVel":"false","yPos":"false","xPos":"false"}}}},"color":{"red":"255","green":"255","blue":"0"},"xpath":{"calculator":{"@attributes":{"type":"parametric"},"value":"0"}},"ypath":{"calculator":{"@attributes":{"type":"parametric"},"value":"h\/2"}}},{"name":"refrayb3","shape":{"@attributes":{"type":"line","drawTrails":"false","drawVectors":"false"},"vectors":{"@attributes":{"yAccel":"false","Vel":"false","xAccel":"false","yVel":"false","xVel":"false","Accel":"false"}},"width":{"calculator":{"@attributes":{"type":"parametric"},"value":"9*cos(var-asin(n3*sin(var-asin(sin(irad)\/n3))))"}},"height":{"calculator":{"@attributes":{"type":"parametric"},"value":"9*sin(var-asin(n3*sin(var-asin(sin(irad)\/n3))))"}},"angle":{"calculator":{"@attributes":{"type":"parametric"},"value":"0"}},"graphOptions":{"@attributes":{"graphVisible":"false"},"initiallyOn":{"@attributes":{"yAccel":"false","yVel":"false","xAccel":"false","xVel":"false","yPos":"false","xPos":"false"}}}},"color":{"red":"255","green":"255","blue":"0"},"xpath":{"calculator":{"@attributes":{"type":"parametric"},"value":"d*cos(asin(irad\/n3))"}},"ypath":{"calculator":{"@attributes":{"type":"parametric"},"value":"d*sin(asin(irad\/n3))+h\/2"}}},{"name":"refraya4","shape":{"@attributes":{"type":"line","drawTrails":"false","drawVectors":"false"},"vectors":{"@attributes":{"yAccel":"false","Vel":"false","xAccel":"false","yVel":"false","xVel":"false","Accel":"false"}},"width":{"calculator":{"@attributes":{"type":"parametric"},"value":"d*cos(asin(irad\/n4))"}},"height":{"calculator":{"@attributes":{"type":"parametric"},"value":"d*sin(asin(irad\/n4))"}},"angle":{"calculator":{"@attributes":{"type":"parametric"},"value":"0"}},"graphOptions":{"@attributes":{"graphVisible":"false"},"initiallyOn":{"@attributes":{"yAccel":"false","yVel":"false","xAccel":"false","xVel":"false","yPos":"false","xPos":"false"}}}},"color":{"red":"0","green":"204","blue":"0"},"xpath":{"calculator":{"@attributes":{"type":"parametric"},"value":"0"}},"ypath":{"calculator":{"@attributes":{"type":"parametric"},"value":"h\/2"}}},{"name":"refrayb4","shape":{"@attributes":{"type":"line","drawTrails":"false","drawVectors":"false"},"vectors":{"@attributes":{"yAccel":"false","Vel":"false","xAccel":"false","yVel":"false","xVel":"false","Accel":"false"}},"width":{"calculator":{"@attributes":{"type":"parametric"},"value":"9*cos(var-asin(n4*sin(var-asin(sin(irad)\/n4))))"}},"height":{"calculator":{"@attributes":{"type":"parametric"},"value":"9*sin(var-asin(n4*sin(var-asin(sin(irad)\/n4))))"}},"angle":{"calculator":{"@attributes":{"type":"parametric"},"value":"0"}},"graphOptions":{"@attributes":{"graphVisible":"false"},"initiallyOn":{"@attributes":{"yAccel":"false","yVel":"false","xAccel":"false","xVel":"false","yPos":"false","xPos":"false"}}}},"color":{"red":"0","green":"204","blue":"0"},"xpath":{"calculator":{"@attributes":{"type":"parametric"},"value":"d*cos(asin(irad\/n4))"}},"ypath":{"calculator":{"@attributes":{"type":"parametric"},"value":"d*sin(asin(irad\/n4))+h\/2"}}},{"name":"refraya5","shape":{"@attributes":{"type":"line","drawTrails":"false","drawVectors":"false"},"vectors":{"@attributes":{"yAccel":"false","Vel":"false","xAccel":"false","yVel":"false","xVel":"false","Accel":"false"}},"width":{"calculator":{"@attributes":{"type":"parametric"},"value":"d*cos(asin(irad\/n5))"}},"height":{"calculator":{"@attributes":{"type":"parametric"},"value":"d*sin(asin(irad\/n5))"}},"angle":{"calculator":{"@attributes":{"type":"parametric"},"value":"0"}},"graphOptions":{"@attributes":{"graphVisible":"false"},"initiallyOn":{"@attributes":{"yAccel":"false","yVel":"false","xAccel":"false","xVel":"false","yPos":"false","xPos":"false"}}}},"color":{"red":"0","green":"51","blue":"255"},"xpath":{"calculator":{"@attributes":{"type":"parametric"},"value":"0"}},"ypath":{"calculator":{"@attributes":{"type":"parametric"},"value":"h\/2"}}},{"name":"refrayb5","shape":{"@attributes":{"type":"line","drawTrails":"false","drawVectors":"false"},"vectors":{"@attributes":{"yAccel":"false","Vel":"false","xAccel":"false","yVel":"false","xVel":"false","Accel":"false"}},"width":{"calculator":{"@attributes":{"type":"parametric"},"value":"9*cos(var-asin(n5*sin(var-asin(sin(irad)\/n5))))"}},"height":{"calculator":{"@attributes":{"type":"parametric"},"value":"9*sin(var-asin(n5*sin(var-asin(sin(irad)\/n5))))"}},"angle":{"calculator":{"@attributes":{"type":"parametric"},"value":"0"}},"graphOptions":{"@attributes":{"graphVisible":"false"},"initiallyOn":{"@attributes":{"yAccel":"false","yVel":"false","xAccel":"false","xVel":"false","yPos":"false","xPos":"false"}}}},"color":{"red":"0","green":"51","blue":"255"},"xpath":{"calculator":{"@attributes":{"type":"parametric"},"value":"d*cos(asin(irad\/n5))"}},"ypath":{"calculator":{"@attributes":{"type":"parametric"},"value":"d*sin(asin(irad\/n5))+h\/2"}}},{"name":"refraya6","shape":{"@attributes":{"type":"line","drawTrails":"false","drawVectors":"false"},"vectors":{"@attributes":{"yAccel":"false","Vel":"false","xAccel":"false","yVel":"false","xVel":"false","Accel":"false"}},"width":{"calculator":{"@attributes":{"type":"parametric"},"value":"d*cos(asin(irad\/n6))"}},"height":{"calculator":{"@attributes":{"type":"parametric"},"value":"d*sin(asin(irad\/n6))"}},"angle":{"calculator":{"@attributes":{"type":"parametric"},"value":"0"}},"graphOptions":{"@attributes":{"graphVisible":"false"},"initiallyOn":{"@attributes":{"yAccel":"false","yVel":"false","xAccel":"false","xVel":"false","yPos":"false","xPos":"false"}}}},"color":{"red":"153","green":"0","blue":"153"},"xpath":{"calculator":{"@attributes":{"type":"parametric"},"value":"0"}},"ypath":{"calculator":{"@attributes":{"type":"parametric"},"value":"h\/2"}}},{"name":"refrayb6","shape":{"@attributes":{"type":"line","drawTrails":"false","drawVectors":"false"},"vectors":{"@attributes":{"yAccel":"false","Vel":"false","xAccel":"false","yVel":"false","xVel":"false","Accel":"false"}},"width":{"calculator":{"@attributes":{"type":"parametric"},"value":"9*cos(var-asin(n6*sin(var-asin(sin(irad)\/n6))))"}},"height":{"calculator":{"@attributes":{"type":"parametric"},"value":"9*sin(var-asin(n6*sin(var-asin(sin(irad)\/n6))))"}},"angle":{"calculator":{"@attributes":{"type":"parametric"},"value":"0"}},"graphOptions":{"@attributes":{"graphVisible":"false"},"initiallyOn":{"@attributes":{"yAccel":"false","yVel":"false","xAccel":"false","xVel":"false","yPos":"false","xPos":"false"}}}},"color":{"red":"153","green":"0","blue":"153"},"xpath":{"calculator":{"@attributes":{"type":"parametric"},"value":"d*cos(asin(irad\/n6))"}},"ypath":{"calculator":{"@attributes":{"type":"parametric"},"value":"d*sin(asin(irad\/n6))+h\/2"}}}]}}