{"author":{"username":{},"name":{},"organization":{},"email":{}},"objects":{"time":{"start":"0.0","stop":"70.0","change":"1.0","fps":"25.0"},"GraphWindow":{"xmin":"0.0","xmax":"50.0","ymin":"-90.0","ymax":"90.0","xgrid":"2.0","ygrid":"5.0"},"window":{"xmin":"-10.0","xmax":"10.0","ymin":"-10.0","ymax":"10.0","xgrid":"2.0","ygrid":"2.0","xunit":"meters","yunit":"meters","showAllDataAvailable":"false","drawGridNumbers":"true"},"description":{"text":"The red line at y = 0 represents a boundary between media of different indices of refraction. The path of a light ray is shown in blue.  Note that both a reflected and a refracted ray are produced at the boundary. This problem is concerned with the refracted ray. Playing the applet forward or backwards will increase or decrease the angle of incidence.  Take measurements from the applet to determine the ratio of the index of refraction of the upper medium to that of the lower medium. You can determine angles of incidence and refraction by finding ratios of the legs of right triangles. In order to improve the accuracy of your measurements, run the applet to obtain the largest angles possible."},"input":[{"name":"angle","text":"Starting angle","initialValue":"20.0","units":"deg","hidden":"1"},{"name":"s","text":"Angle increment","initialValue":"1.0","units":"deg","hidden":"1"},{"name":"n","text":"n2\/n1","initialValue":"1.45","units":{},"hidden":"1"}],"output":[{"name":"i","text":"Angle of incidence","units":"deg","calculator":{"@attributes":{"type":"parametric"},"value":"angle+s*t"}},{"name":"r","text":"Angle of refraction","units":"deg","calculator":{"@attributes":{"type":"parametric"},"value":"toDegrees(asin(sin(toRadians(i))\/n))"},"hidden":"1"},{"name":"ac","text":"Critical angle","units":"deg","calculator":{"@attributes":{"type":"parametric"},"value":"toDegrees(asin(n))"},"hidden":"1"}],"solid":[{"name":"boundary","shape":{"@attributes":{"type":"line","drawTrails":"false","drawVectors":"false"},"vectors":{"@attributes":{"yAccel":"false","Vel":"false","xAccel":"false","yVel":"false","xVel":"false","Accel":"false"}},"width":{"calculator":{"@attributes":{"type":"parametric"},"value":"20"}},"height":{"calculator":{"@attributes":{"type":"parametric"},"value":"0"}},"angle":{"calculator":{"@attributes":{"type":"parametric"},"value":"0"}},"graphOptions":{"@attributes":{"graphVisible":"false"},"initiallyOn":{"@attributes":{"yAccel":"false","yVel":"false","xAccel":"false","xVel":"false","yPos":"false","xPos":"false"}}}},"color":{"red":"255","green":"0","blue":"51"},"xpath":{"calculator":{"@attributes":{"type":"parametric"},"value":"-10"}},"ypath":{"calculator":{"@attributes":{"type":"parametric"},"value":"0"}}},{"name":"incidentray","shape":{"@attributes":{"type":"vector","drawTrails":"false","drawVectors":"false"},"vectors":{"@attributes":{"yAccel":"false","Vel":"false","xAccel":"false","yVel":"false","xVel":"false","Accel":"false"}},"width":{"calculator":{"@attributes":{"type":"parametric"},"value":"10*tan(toRadians(i))"}},"height":{"calculator":{"@attributes":{"type":"parametric"},"value":"10"}},"angle":{"calculator":{"@attributes":{"type":"parametric"},"value":"0"}},"graphOptions":{"@attributes":{"graphVisible":"false"},"initiallyOn":{"@attributes":{"yAccel":"false","yVel":"false","xAccel":"false","xVel":"false","yPos":"false","xPos":"false"}}}},"color":{"red":"51","green":"0","blue":"204"},"xpath":{"calculator":{"@attributes":{"type":"parametric"},"value":"-10*tan(toRadians(i))"}},"ypath":{"calculator":{"@attributes":{"type":"parametric"},"value":"-10"}}},{"name":"refractedray","shape":{"@attributes":{"type":"vector","drawTrails":"false","drawVectors":"false"},"vectors":{"@attributes":{"yAccel":"false","Vel":"false","xAccel":"false","yVel":"false","xVel":"false","Accel":"false"}},"width":{"calculator":{"@attributes":{"type":"parametric"},"value":"10*tan(asin(sin(toRadians(i))\/n))"}},"height":{"calculator":{"@attributes":{"type":"parametric"},"value":"10"}},"angle":{"calculator":{"@attributes":{"type":"parametric"},"value":"0"}},"graphOptions":{"@attributes":{"graphVisible":"false"},"initiallyOn":{"@attributes":{"yAccel":"false","yVel":"false","xAccel":"false","xVel":"false","yPos":"false","xPos":"false"}}}},"color":{"red":"0","green":"0","blue":"204"},"xpath":{"calculator":{"@attributes":{"type":"parametric"},"value":"0"}},"ypath":{"calculator":{"@attributes":{"type":"parametric"},"value":"0"}}},{"name":"reflectedray","shape":{"@attributes":{"type":"vector","drawTrails":"false","drawVectors":"false"},"vectors":{"@attributes":{"yAccel":"false","Vel":"false","xAccel":"false","yVel":"false","xVel":"false","Accel":"false"}},"width":{"calculator":{"@attributes":{"type":"parametric"},"value":"10*tan(toRadians(i))"}},"height":{"calculator":{"@attributes":{"type":"parametric"},"value":"-10"}},"angle":{"calculator":{"@attributes":{"type":"parametric"},"value":"0"}},"graphOptions":{"@attributes":{"graphVisible":"false"},"initiallyOn":{"@attributes":{"yAccel":"false","yVel":"false","xAccel":"false","xVel":"false","yPos":"false","xPos":"false"}}}},"color":{"red":"0","green":"0","blue":"204"},"xpath":{"calculator":{"@attributes":{"type":"parametric"},"value":"0"}},"ypath":{"calculator":{"@attributes":{"type":"parametric"},"value":"0"}}}],"object":[{"@attributes":{"class":"edu.ncssm.iwp.objects.floatingtext.DObject_FloatingText"},"name":"medium_1","text":"Medium of incidence","units":{},"value":{"calculator":{"@attributes":{"type":"parametric"},"value":"0"}},"fontSize":"12","showValue":"false","color":{"red":"0","green":"0","blue":"0"},"ypath":{"calculator":{"@attributes":{"type":"parametric"},"value":"-1"}},"xpath":{"calculator":{"@attributes":{"type":"parametric"},"value":"3"}}},{"@attributes":{"class":"edu.ncssm.iwp.objects.floatingtext.DObject_FloatingText"},"name":"medium_2","text":"Medium of refraction","units":{},"value":{"calculator":{"@attributes":{"type":"parametric"},"value":"0"}},"fontSize":"12","showValue":"false","color":{"red":"0","green":"0","blue":"0"},"ypath":{"calculator":{"@attributes":{"type":"parametric"},"value":".7"}},"xpath":{"calculator":{"@attributes":{"type":"parametric"},"value":"3"}}}]}}