{"author":{"username":"winters@ncssm.edu","name":{},"organization":{},"email":{}},"objects":{"time":{"start":"0.0","stop":"5.0","change":"0.05","fps":"20.0"},"GraphWindow":{"xmin":"0.0","xmax":"2.0","ymin":"-20.0","ymax":"20.0","xgrid":"0.2","ygrid":"2.0"},"window":{"xmin":"-0.5","xmax":"21.5","ymin":"-0.5","ymax":"21.5","xgrid":"2.0","ygrid":"2.0","xunit":"meters","yunit":"meters","showAllDataAvailable":"false","drawGridNumbers":"true"},"description":{"text":"What is the angle of launch of the ball necessary to hit the falling target?"},"input":[{"name":"g","text":"gravity field","initialValue":"-9.8","units":"N\/kg","hidden":"1"},{"name":"v","text":"Initial speed of ball","initialValue":"15.0","units":"m\/s","hidden":"1"},{"name":"a","text":"Angle of launch","initialValue":"21.8","units":"deg","hidden":"1"},{"name":"ht","text":"Initial height of target","initialValue":"18.0","units":"m","hidden":"1"},{"name":"vt","text":"Initial velocity of target","initialValue":"0.0","units":"m\/s","hidden":"1"}],"solid":[{"name":"target","shape":{"@attributes":{"type":"rectangle","drawTrails":"false","drawVectors":"false"},"vectors":{"@attributes":{"yAccel":"false","Vel":"false","xAccel":"false","yVel":"false","xVel":"false","Accel":"false"}},"width":{"calculator":{"@attributes":{"type":"parametric"},"value":"1"}},"height":{"calculator":{"@attributes":{"type":"parametric"},"value":"1"}},"angle":{"calculator":{"@attributes":{"type":"parametric"},"value":"0"}},"graphOptions":{"@attributes":{"graphVisible":"false"},"initiallyOn":{"@attributes":{"yAccel":"false","yVel":"false","xAccel":"false","xVel":"false","yPos":"false","xPos":"false"}}}},"color":{"red":"0","green":"204","blue":"51"},"xpath":{"calculator":{"@attributes":{"type":"parametric"},"value":"20"}},"ypath":{"calculator":{"@attributes":{"type":"parametric"},"value":"ht+0.5*g*t^2"}}},{"name":"gun_height","shape":{"@attributes":{"type":"rectangle","drawTrails":"false","drawVectors":"false"},"vectors":{"@attributes":{"yAccel":"false","Vel":"false","xAccel":"false","yVel":"false","xVel":"false","Accel":"false"}},"width":{"calculator":{"@attributes":{"type":"parametric"},"value":"1"}},"height":{"calculator":{"@attributes":{"type":"parametric"},"value":"10"}},"angle":{"calculator":{"@attributes":{"type":"parametric"},"value":"0"}},"graphOptions":{"@attributes":{"graphVisible":"false"},"initiallyOn":{"@attributes":{"yAccel":"false","yVel":"false","xAccel":"false","xVel":"false","yPos":"false","xPos":"false"}}}},"color":{"red":"51","green":"51","blue":"255"},"xpath":{"calculator":{"@attributes":{"type":"parametric"},"value":"0"}},"ypath":{"calculator":{"@attributes":{"type":"parametric"},"value":"4.5"}}},{"name":"wall","shape":{"@attributes":{"type":"rectangle","drawTrails":"false","drawVectors":"false"},"vectors":{"@attributes":{"yAccel":"false","Vel":"false","xAccel":"false","yVel":"false","xVel":"false","Accel":"false"}},"width":{"calculator":{"@attributes":{"type":"parametric"},"value":"1"}},"height":{"calculator":{"@attributes":{"type":"parametric"},"value":"22"}},"angle":{"calculator":{"@attributes":{"type":"parametric"},"value":"0"}},"graphOptions":{"@attributes":{"graphVisible":"false"},"initiallyOn":{"@attributes":{"yAccel":"false","yVel":"false","xAccel":"false","xVel":"false","yPos":"false","xPos":"false"}}}},"color":{"red":"51","green":"51","blue":"255"},"xpath":{"calculator":{"@attributes":{"type":"parametric"},"value":"21"}},"ypath":{"calculator":{"@attributes":{"type":"parametric"},"value":"10"}}},{"name":"floor","shape":{"@attributes":{"type":"rectangle","drawTrails":"false","drawVectors":"false"},"vectors":{"@attributes":{"yAccel":"false","Vel":"false","xAccel":"false","yVel":"false","xVel":"false","Accel":"false"}},"width":{"calculator":{"@attributes":{"type":"parametric"},"value":"21"}},"height":{"calculator":{"@attributes":{"type":"parametric"},"value":"1"}},"angle":{"calculator":{"@attributes":{"type":"parametric"},"value":"0"}},"graphOptions":{"@attributes":{"graphVisible":"false"},"initiallyOn":{"@attributes":{"yAccel":"false","yVel":"false","xAccel":"false","xVel":"false","yPos":"false","xPos":"false"}}}},"color":{"red":"51","green":"51","blue":"255"},"xpath":{"calculator":{"@attributes":{"type":"parametric"},"value":"10"}},"ypath":{"calculator":{"@attributes":{"type":"parametric"},"value":"0"}}},{"name":"ball","shape":{"@attributes":{"type":"circle","drawTrails":"true","drawVectors":"false"},"vectors":{"@attributes":{"yAccel":"false","Vel":"false","xAccel":"false","yVel":"false","xVel":"false","Accel":"false"}},"width":{"calculator":{"@attributes":{"type":"parametric"},"value":"1"}},"height":{"calculator":{"@attributes":{"type":"parametric"},"value":"1"}},"angle":{"calculator":{"@attributes":{"type":"parametric"},"value":"0"}},"graphOptions":{"@attributes":{"graphVisible":"false"},"initiallyOn":{"@attributes":{"yAccel":"false","yVel":"false","xAccel":"false","xVel":"false","yPos":"false","xPos":"false"}}}},"color":{"red":"255","green":"51","blue":"51"},"xpath":{"calculator":{"@attributes":{"type":"parametric"},"value":"v*cos(toRadians(a))*t"}},"ypath":{"calculator":{"@attributes":{"type":"parametric"},"value":"10+v*sin(toRadians(a))*t+.5*g*t^2"}}}],"output":[{"name":"x","text":"Ball X","units":"m","calculator":{"@attributes":{"type":"parametric"},"value":"ball.xpos"}},{"name":"y","text":"Ball Y","units":"m","calculator":{"@attributes":{"type":"parametric"},"value":"ball.ypos"}},{"name":"yt","text":"Target Y","units":"m","calculator":{"@attributes":{"type":"parametric"},"value":"target.ypos"}}]}}