{"author":{"username":"winters@ncssm.edu","name":{},"organization":{},"email":{}},"objects":{"time":{"start":"0.0","stop":"2.0E-8","change":"1.0E-10","fps":"25.0"},"GraphWindow":{"xmin":"0.0","xmax":"2.0E-8","ymin":"-0.07","ymax":"0.07","xgrid":"1.0E-9","ygrid":"0.0070"},"window":{"xmin":"-0.075","xmax":"0.125","ymin":"-0.1","ymax":"0.1","xgrid":"0.01","ygrid":"0.01","xunit":"meters","yunit":"meters"},"description":{"text":"An electron is accelerated from rest under the influence of a potential V. At the origin, the electron enters crossed electric and magnetic fields.  The electric field is oriented in the -y direction and is produced by parallel plates with a potential difference equal to V.  The magnetic field is oriented in the -z direction (into screen) and is produced by Helmholtz coils.\nVectors:  red = velocity     green = magnetic force     black = electric force  \nblue = acceleration\n"},"input":[{"name":"size","text":"Size scale","initialValue":"0.0030","units":{},"hidden":"1"},{"name":"R","text":"Charge to mass ratio","initialValue":"1.756E11","units":"C\/kg","hidden":"1"},{"name":"s","text":"Sign of charge","initialValue":"-1.0","units":{},"hidden":"1"},{"name":"u","text":"B-field ON = 1 or OFF = 0","initialValue":"1.0","units":{}},{"name":"z","text":"E-field ON = 1 or OFF = 0","initialValue":"1.0","units":{}},{"name":"d","text":"Plate separation","initialValue":"0.06","units":"m"},{"name":"V1","text":"Accelerating potential","initialValue":"2000.0","units":"V"},{"name":"r","text":"Coil radius\/separation","initialValue":"0.07","units":"m"},{"name":"n","text":"Turns per coil","initialValue":"320.0","units":{}},{"name":"i","text":"Coil current","initialValue":"0.75","units":"A"},{"name":"x","text":"Acceleration distance","initialValue":"0.05","units":"m","hidden":"1"},{"name":"xc","text":"Coasting distance","initialValue":"0.02","units":"m","hidden":"1"},{"name":"vscale","text":"Scale Factor for V","initialValue":"1.0E-9","units":{},"hidden":"1"},{"name":"fscale","text":"Scale factor for force","initialValue":"4.0E-7","units":{},"hidden":"1"}],"output":[{"name":"tf","text":"Time in fields","units":"s","calculator":{"@attributes":{"type":"parametric"},"value":"(t-to-t1)*step(t-to-t1)"}},{"name":"V2","text":"Plate potential","units":"V","calculator":{"@attributes":{"type":"parametric"},"value":"V1*z"}},{"name":"vo","text":"Entry velocity","units":"m\/s","calculator":{"@attributes":{"type":"parametric"},"value":"(2*R*V1)^.5"}},{"name":"Ef","text":"Electric field","units":"V\/m","calculator":{"@attributes":{"type":"parametric"},"value":"s*V2\/d"}},{"name":"B","text":"Magnetic field","units":"T","calculator":{"@attributes":{"type":"parametric"},"value":"u*s*0.000000899*i*n\/r"}},{"name":"to","text":"Time to plates","units":"s","calculator":{"@attributes":{"type":"parametric"},"value":"2*x\/vo"},"hidden":"1"},{"name":"t1","text":"Time to coast","units":"s","calculator":{"@attributes":{"type":"parametric"},"value":"xc\/vo"},"hidden":"1"},{"name":"px","text":"X-position","units":"m","calculator":{"@attributes":{"type":"parametric"},"value":"P.xpos"}},{"name":"py","text":"Y-position","units":"m","calculator":{"@attributes":{"type":"parametric"},"value":"P.ypos"}}],"solid":[{"name":"coil1","shape":{"@attributes":{"type":"circle","drawTrails":"false","drawVectors":"false"},"vectors":{"@attributes":{"yAccel":"false","Vel":"false","xAccel":"false","yVel":"false","xVel":"false","Accel":"false"}},"width":{"calculator":{"@attributes":{"type":"parametric"},"value":"r*2*u"}},"height":{"calculator":{"@attributes":{"type":"parametric"},"value":"r*2*u"}},"graphOptions":{"@attributes":{"graphVisible":"false"},"initiallyOn":{"@attributes":{"yAccel":"false","yVel":"false","xAccel":"false","xVel":"false","yPos":"false","xPos":"false"}}}},"color":{"red":"0","green":"204","blue":"0"},"xpath":{"calculator":{"@attributes":{"type":"parametric"},"value":".055"}},"ypath":{"calculator":{"@attributes":{"type":"parametric"},"value":"0"}}},{"name":"coil2","shape":{"@attributes":{"type":"circle","drawTrails":"false","drawVectors":"false"},"vectors":{"@attributes":{"yAccel":"false","Vel":"false","xAccel":"false","yVel":"false","xVel":"false","Accel":"false"}},"width":{"calculator":{"@attributes":{"type":"parametric"},"value":"r*1.9*u"}},"height":{"calculator":{"@attributes":{"type":"parametric"},"value":"r*1.9*u"}},"graphOptions":{"@attributes":{"graphVisible":"false"},"initiallyOn":{"@attributes":{"yAccel":"false","yVel":"false","xAccel":"false","xVel":"false","yPos":"false","xPos":"false"}}}},"color":{"red":"255","green":"255","blue":"255"},"xpath":{"calculator":{"@attributes":{"type":"parametric"},"value":".055"}},"ypath":{"calculator":{"@attributes":{"type":"parametric"},"value":"0"}}},{"name":"plate1","shape":{"@attributes":{"type":"rectangle","drawTrails":"false","drawVectors":"false"},"vectors":{"@attributes":{"yAccel":"false","Vel":"false","xAccel":"false","yVel":"false","xVel":"false","Accel":"false"}},"width":{"calculator":{"@attributes":{"type":"parametric"},"value":".11"}},"height":{"calculator":{"@attributes":{"type":"parametric"},"value":"z*size\/2"}},"graphOptions":{"@attributes":{"graphVisible":"false"},"initiallyOn":{"@attributes":{"yAccel":"false","yVel":"false","xAccel":"false","xVel":"false","yPos":"false","xPos":"false"}}}},"color":{"red":"102","green":"102","blue":"102"},"xpath":{"calculator":{"@attributes":{"type":"parametric"},"value":".055"}},"ypath":{"calculator":{"@attributes":{"type":"parametric"},"value":"d\/2+size\/4"}}},{"name":"plate2","shape":{"@attributes":{"type":"rectangle","drawTrails":"false","drawVectors":"false"},"vectors":{"@attributes":{"yAccel":"false","Vel":"false","xAccel":"false","yVel":"false","xVel":"false","Accel":"false"}},"width":{"calculator":{"@attributes":{"type":"parametric"},"value":".11"}},"height":{"calculator":{"@attributes":{"type":"parametric"},"value":"z*size\/2"}},"graphOptions":{"@attributes":{"graphVisible":"false"},"initiallyOn":{"@attributes":{"yAccel":"false","yVel":"false","xAccel":"false","xVel":"false","yPos":"false","xPos":"false"}}}},"color":{"red":"102","green":"102","blue":"102"},"xpath":{"calculator":{"@attributes":{"type":"parametric"},"value":".055"}},"ypath":{"calculator":{"@attributes":{"type":"parametric"},"value":"-d\/2-size\/4"}}},{"name":"gun","shape":{"@attributes":{"type":"rectangle","drawTrails":"false","drawVectors":"false"},"vectors":{"@attributes":{"yAccel":"false","Vel":"false","xAccel":"false","yVel":"false","xVel":"false","Accel":"false"}},"width":{"calculator":{"@attributes":{"type":"parametric"},"value":"x"}},"height":{"calculator":{"@attributes":{"type":"parametric"},"value":"2*size"}},"graphOptions":{"@attributes":{"graphVisible":"false"},"initiallyOn":{"@attributes":{"yAccel":"false","yVel":"false","xAccel":"false","xVel":"false","yPos":"false","xPos":"false"}}}},"color":{"red":"204","green":"204","blue":"204"},"xpath":{"calculator":{"@attributes":{"type":"parametric"},"value":"-(x\/2+xc)"}},"ypath":{"calculator":{"@attributes":{"type":"parametric"},"value":"0"}}},{"name":"vvect","shape":{"@attributes":{"type":"vector","drawTrails":"false","drawVectors":"false"},"vectors":{"@attributes":{"yAccel":"false","Vel":"false","xAccel":"false","yVel":"false","xVel":"false","Accel":"false"}},"width":{"calculator":{"@attributes":{"type":"parametric"},"value":"vscale*P.xvel"}},"height":{"calculator":{"@attributes":{"type":"parametric"},"value":"vscale*P.yvel"}},"graphOptions":{"@attributes":{"graphVisible":"false"},"initiallyOn":{"@attributes":{"yAccel":"false","yVel":"false","xAccel":"false","xVel":"false","yPos":"false","xPos":"false"}}}},"color":{"red":"255","green":"0","blue":"51"},"xpath":{"calculator":{"@attributes":{"type":"parametric"},"value":"P.xpos"}},"ypath":{"calculator":{"@attributes":{"type":"parametric"},"value":"P.ypos"}}},{"name":"fnetvect","shape":{"@attributes":{"type":"vector","drawTrails":"false","drawVectors":"false"},"vectors":{"@attributes":{"yAccel":"false","Vel":"false","xAccel":"false","yVel":"false","xVel":"false","Accel":"false"}},"width":{"calculator":{"@attributes":{"type":"parametric"},"value":"(s*B*P.yvel*step(t-to-t1)+(V1\/x)*step(to-t))*fscale"}},"height":{"calculator":{"@attributes":{"type":"parametric"},"value":"s*(E-B*P.xvel)*step(t-to-t1)*fscale"}},"graphOptions":{"@attributes":{"graphVisible":"false"},"initiallyOn":{"@attributes":{"yAccel":"false","yVel":"false","xAccel":"false","xVel":"false","yPos":"false","xPos":"false"}}}},"color":{"red":"0","green":"51","blue":"255"},"xpath":{"calculator":{"@attributes":{"type":"parametric"},"value":"P.xpos"}},"ypath":{"calculator":{"@attributes":{"type":"parametric"},"value":"P.ypos"}}},{"name":"fevect","shape":{"@attributes":{"type":"vector","drawTrails":"false","drawVectors":"false"},"vectors":{"@attributes":{"yAccel":"false","Vel":"false","xAccel":"false","yVel":"false","xVel":"false","Accel":"false"}},"width":{"calculator":{"@attributes":{"type":"parametric"},"value":"0"}},"height":{"calculator":{"@attributes":{"type":"parametric"},"value":"s*E*fscale*step(t-to-t1)"}},"graphOptions":{"@attributes":{"graphVisible":"false"},"initiallyOn":{"@attributes":{"yAccel":"false","yVel":"false","xAccel":"false","xVel":"false","yPos":"false","xPos":"false"}}}},"color":{"red":"0","green":"51","blue":"51"},"xpath":{"calculator":{"@attributes":{"type":"parametric"},"value":"P.xpos"}},"ypath":{"calculator":{"@attributes":{"type":"parametric"},"value":"P.ypos"}}},{"name":"fmvect","shape":{"@attributes":{"type":"vector","drawTrails":"false","drawVectors":"false"},"vectors":{"@attributes":{"yAccel":"false","Vel":"false","xAccel":"false","yVel":"false","xVel":"false","Accel":"false"}},"width":{"calculator":{"@attributes":{"type":"parametric"},"value":"s*B*P.yvel*fscale*step(t-to-t1)"}},"height":{"calculator":{"@attributes":{"type":"parametric"},"value":"-s*B*P.xvel*fscale*step(t-to-t1)"}},"graphOptions":{"@attributes":{"graphVisible":"false"},"initiallyOn":{"@attributes":{"yAccel":"false","yVel":"false","xAccel":"false","xVel":"false","yPos":"false","xPos":"false"}}}},"color":{"red":"0","green":"204","blue":"51"},"xpath":{"calculator":{"@attributes":{"type":"parametric"},"value":"P.xpos"}},"ypath":{"calculator":{"@attributes":{"type":"parametric"},"value":"P.ypos"}}},{"name":"P","shape":{"@attributes":{"type":"circle","drawTrails":"true","drawVectors":"false"},"vectors":{"@attributes":{"yAccel":"false","Vel":"false","xAccel":"false","yVel":"false","xVel":"false","Accel":"false"}},"width":{"calculator":{"@attributes":{"type":"parametric"},"value":"size"}},"height":{"calculator":{"@attributes":{"type":"parametric"},"value":"size"}},"graphOptions":{"@attributes":{"graphVisible":"true"},"initiallyOn":{"@attributes":{"yAccel":"false","yVel":"false","xAccel":"false","xVel":"false","yPos":"true","xPos":"true"}}}},"color":{"red":"255","green":"0","blue":"0"},"xpath":{"calculator":{"@attributes":{"type":"euler"},"displacement":"-x-xc","velocity":"0","acceleration":"s*(R*B*P.yvel*step(t-to-t1)+R*(V1\/x)*step(to-t))"}},"ypath":{"calculator":{"@attributes":{"type":"euler"},"displacement":"0","velocity":"0","acceleration":"s*R*(Ef-B*P.xvel)*step(t-to-t1)"}}}]}}