{"author":{"username":"winters@ncssm.edu","name":{},"organization":{},"email":{}},"objects":{"time":{"start":"0.0","stop":"100.0","change":"0.05","fps":"20.0"},"GraphWindow":{"xmin":"0.0","xmax":"10.0","ymin":"-10.0","ymax":"10.0","xgrid":"1.0","ygrid":"2.0"},"window":{"xmin":"-1.5","xmax":"1.5","ymin":"-2.5","ymax":"0.5","xgrid":"1.5","ygrid":"2.5","xunit":"meters","yunit":"meters","showAllDataAvailable":"false","drawGridNumbers":"true"},"description":{"text":"Note that the period output returns an imaginary number because d\/g is calculated as negative."},"input":[{"name":"d","text":"Length","initialValue":"2.0","units":"m"},{"name":"a","text":"Initial angle","initialValue":"10.0","units":"deg"},{"name":"g","text":"Gravitational Field","initialValue":"9.8","units":"N\/kg","hidden":"1"},{"name":"m","text":"Mass of bob","initialValue":"0.4","units":"kg"}],"solid":[{"name":"bob","shape":{"@attributes":{"type":"circle","drawTrails":"false","drawVectors":"false"},"vectors":{"@attributes":{"yAccel":"false","Vel":"false","xAccel":"false","yVel":"false","xVel":"false","Accel":"false"}},"width":{"calculator":{"@attributes":{"type":"parametric"},"value":".25"}},"height":{"calculator":{"@attributes":{"type":"parametric"},"value":".25"}},"angle":{"calculator":{"@attributes":{"type":"parametric"},"value":"0"}},"graphOptions":{"@attributes":{"graphVisible":"false"},"initiallyOn":{"@attributes":{"yAccel":"false","yVel":"false","xAccel":"false","xVel":"false","yPos":"false","xPos":"false"}}}},"color":{"red":"255","green":"0","blue":"51"},"xpath":{"calculator":{"@attributes":{"type":"euler"},"displacement":"-d.value*sin(toRadians(a))","velocity":"0","acceleration":"g.value*bob.xdisp*bob.ydisp\/d.value^2-(bob.xvel^2+bob.yvel^2)*bob.xdisp\/d.value^2"}},"ypath":{"calculator":{"@attributes":{"type":"euler"},"displacement":"-d.value*cos(toRadians(a))","velocity":"0","acceleration":"-g.value*(bob.xdisp\/d.value)^2-(bob.xvel^2+bob.yvel^2)*bob.ydisp\/d.value^2"}}},{"name":"string","shape":{"@attributes":{"type":"line","drawTrails":"false","drawVectors":"false"},"vectors":{"@attributes":{"yAccel":"false","Vel":"false","xAccel":"false","yVel":"false","xVel":"false","Accel":"false"}},"width":{"calculator":{"@attributes":{"type":"parametric"},"value":"bob.xpos"}},"height":{"calculator":{"@attributes":{"type":"parametric"},"value":"bob.ypos"}},"angle":{"calculator":{"@attributes":{"type":"parametric"},"value":"0"}},"graphOptions":{"@attributes":{"graphVisible":"false"},"initiallyOn":{"@attributes":{"yAccel":"false","yVel":"false","xAccel":"false","xVel":"false","yPos":"false","xPos":"false"}}}},"color":{"red":"0","green":"0","blue":"0"},"xpath":{"calculator":{"@attributes":{"type":"parametric"},"value":"0"}},"ypath":{"calculator":{"@attributes":{"type":"parametric"},"value":"0"}}},{"name":"support","shape":{"@attributes":{"type":"rectangle","drawTrails":"false","drawVectors":"false"},"vectors":{"@attributes":{"yAccel":"false","Vel":"false","xAccel":"false","yVel":"false","xVel":"false","Accel":"false"}},"width":{"calculator":{"@attributes":{"type":"parametric"},"value":"3"}},"height":{"calculator":{"@attributes":{"type":"parametric"},"value":".5"}},"angle":{"calculator":{"@attributes":{"type":"parametric"},"value":"0"}},"graphOptions":{"@attributes":{"graphVisible":"false"},"initiallyOn":{"@attributes":{"yAccel":"false","yVel":"false","xAccel":"false","xVel":"false","yPos":"false","xPos":"false"}}}},"color":{"red":"102","green":"0","blue":"0"},"xpath":{"calculator":{"@attributes":{"type":"parametric"},"value":"0"}},"ypath":{"calculator":{"@attributes":{"type":"parametric"},"value":"0.25"}}}],"output":[{"name":"x","text":"Bob's x-coordinate","units":"m","calculator":{"@attributes":{"type":"parametric"},"value":"bob.xpos"},"hidden":"1"},{"name":"y","text":"Bob's y-coordinate","units":"m","calculator":{"@attributes":{"type":"parametric"},"value":"bob.ypos"},"hidden":"1"},{"name":"P","text":"Period","units":"s","calculator":{"@attributes":{"type":"parametric"},"value":"2*3.14159*(d\/g)^.5"}}]}}