{"author":{"username":{},"name":{},"organization":{},"email":{}},"objects":{"time":{"start":"0.0","stop":"100.0","change":"0.01","fps":"50.0"},"GraphWindow":{"xmin":"0.0","xmax":"100.0","ymin":"-10.0","ymax":"10.0","xgrid":"2.0","ygrid":"2.0"},"window":{"xmin":"-5.0","xmax":"5.0","ymin":"-9.0","ymax":"1.0","xgrid":"1.0","ygrid":"1.0"},"description":{"text":"Blue is Eulers\nRed is RK4"},"input":[{"name":"d","text":"Length","initialValue":"7.0","units":"m"},{"name":"angle","text":"Initial angle","initialValue":"30.0","units":"deg"},{"name":"g","text":"Gravitational Field","initialValue":"9.8","units":"N\/kg"},{"name":"n","text":"Make negative","initialValue":"-1.0","units":{},"hidden":"1"}],"solid":[{"name":"bob","shape":{"@attributes":{"type":"circle"},"width":{"calculator":{"@attributes":{"type":"parametric"},"value":".2"}},"height":{"calculator":{"@attributes":{"type":"parametric"},"value":".2"}},"graphOptions":{"@attributes":{"graphVisible":"true"},"initiallyOn":{"@attributes":{"yAccel":"false","yVel":"false","xAccel":"false","xVel":"false","yPos":"false","xPos":"false"}}}},"color":{"red":"51","green":"51","blue":"255"},"xpath":{"calculator":{"@attributes":{"type":"euler"},"displacement":"n.value*d.value*sin(toRadians(angle.value))","velocity":"0","acceleration":"g.value*bob.xdisp*bob.ydisp\/d.value^2-(bob.xvel^2+bob.yvel^2)*bob.xdisp\/d.value^2"}},"ypath":{"calculator":{"@attributes":{"type":"euler"},"displacement":"n.value*d.value*cos(toRadians(angle.value))","velocity":"0","acceleration":"n.value*g.value*(bob.xdisp\/d.value)^2-(bob.xvel^2+bob.yvel^2)*bob.ydisp\/d.value^2"}}},{"name":"bob_clone","shape":{"@attributes":{"type":"circle"},"width":{"calculator":{"@attributes":{"type":"parametric"},"value":".2"}},"height":{"calculator":{"@attributes":{"type":"parametric"},"value":".2"}},"graphOptions":{"@attributes":{"graphVisible":"true"},"initiallyOn":{"@attributes":{"yAccel":"false","yVel":"false","xAccel":"false","xVel":"false","yPos":"false","xPos":"false"}}}},"color":{"red":"255","green":"51","blue":"51"},"xpath":{"calculator":{"@attributes":{"type":"RK4"},"displacement":"n.value*d.value*sin(toRadians(angle.value))","velocity":"0","acceleration":"g.value*bob.xdisp*bob.ydisp\/d.value^2-(bob.xvel^2+bob.yvel^2)*bob.xdisp\/d.value^2"}},"ypath":{"calculator":{"@attributes":{"type":"RK4"},"displacement":"n.value*d.value*cos(toRadians(angle.value))","velocity":"0","acceleration":"n.value*g.value*(bob.xdisp\/d.value)^2-(bob.xvel^2+bob.yvel^2)*bob.ydisp\/d.value^2"}}}],"output":[{"name":"ax","text":"X Acceleration","units":"m\/s\u00b2","calculator":{"@attributes":{"type":"parametric"},"value":"bob.xaccel"}},{"name":"ay","text":"Y Acceleration","units":"m\/s\u00b2","calculator":{"@attributes":{"type":"parametric"},"value":"bob.yaccel"}},{"name":"x","text":"X Position","units":"m","calculator":{"@attributes":{"type":"parametric"},"value":"bob.xdisp"}},{"name":"y","text":"Y Position","units":"m","calculator":{"@attributes":{"type":"parametric"},"value":"bob.ydisp"}},{"name":"vsquared","text":"Speed\u00b2","units":"m\u00b2\/s\u00b2","calculator":{"@attributes":{"type":"parametric"},"value":"(bob.xvel)^2+(bob.yvel)^2"}}]}}