{"author":{"username":{},"name":{},"organization":{},"email":{}},"objects":{"time":{"start":"0.0","stop":"10.0","change":"0.01","fps":"10.0"},"GraphWindow":{"xmin":"0.0","xmax":"10.0","ymin":"-10.0","ymax":"10.0","xgrid":"2.0","ygrid":"2.0"},"window":{"xmin":"-11.0","xmax":"1.0","ymin":"-10.0","ymax":"10.0","xgrid":"2.0","ygrid":"2.0","xunit":"m","yunit":"m","showAllDataAvailable":"false","drawGridNumbers":"true"},"description":{"text":"The fundamental frequency is produced in closed and open pipes of equal lengths. How to the frequencies produced by the pipes compare?  How long would the closed pipe have to be to have the same fundamental frequency as the open pipe?  (What does it take to make the wavelengths equal in both pipes.)"},"solid":[{"name":"bg","shape":{"@attributes":{"type":"rectangle","drawTrails":"false","drawVectors":"false"},"vectors":{"@attributes":{"yAccel":"false","Vel":"false","xAccel":"false","yVel":"false","xVel":"false","Accel":"false"}},"width":{"calculator":{"@attributes":{"type":"parametric"},"value":"24"}},"height":{"calculator":{"@attributes":{"type":"parametric"},"value":"24"}},"angle":{"calculator":{"@attributes":{"type":"parametric"},"value":"0"}},"graphOptions":{"@attributes":{"graphVisible":"false"},"initiallyOn":{"@attributes":{"yAccel":"false","yVel":"false","xAccel":"false","xVel":"false","yPos":"false","xPos":"false"}}}},"color":{"red":"153","green":"153","blue":"153"},"xpath":{"calculator":{"@attributes":{"type":"parametric"},"value":"0"}},"ypath":{"calculator":{"@attributes":{"type":"parametric"},"value":"0"}}},{"name":"bg_1","shape":{"@attributes":{"type":"rectangle","drawTrails":"false","drawVectors":"false"},"vectors":{"@attributes":{"yAccel":"false","Vel":"false","xAccel":"false","yVel":"false","xVel":"false","Accel":"false"}},"width":{"calculator":{"@attributes":{"type":"parametric"},"value":"20"}},"height":{"calculator":{"@attributes":{"type":"parametric"},"value":"4"}},"angle":{"calculator":{"@attributes":{"type":"parametric"},"value":"0"}},"graphOptions":{"@attributes":{"graphVisible":"false"},"initiallyOn":{"@attributes":{"yAccel":"false","yVel":"false","xAccel":"false","xVel":"false","yPos":"false","xPos":"false"}}}},"color":{"red":"255","green":"255","blue":"255"},"xpath":{"calculator":{"@attributes":{"type":"parametric"},"value":"0"}},"ypath":{"calculator":{"@attributes":{"type":"parametric"},"value":"5"}}},{"name":"bg_2","shape":{"@attributes":{"type":"rectangle","drawTrails":"false","drawVectors":"false"},"vectors":{"@attributes":{"yAccel":"false","Vel":"false","xAccel":"false","yVel":"false","xVel":"false","Accel":"false"}},"width":{"calculator":{"@attributes":{"type":"parametric"},"value":"20"}},"height":{"calculator":{"@attributes":{"type":"parametric"},"value":"4"}},"angle":{"calculator":{"@attributes":{"type":"parametric"},"value":"0"}},"graphOptions":{"@attributes":{"graphVisible":"false"},"initiallyOn":{"@attributes":{"yAccel":"false","yVel":"false","xAccel":"false","xVel":"false","yPos":"false","xPos":"false"}}}},"color":{"red":"255","green":"255","blue":"255"},"xpath":{"calculator":{"@attributes":{"type":"parametric"},"value":"0"}},"ypath":{"calculator":{"@attributes":{"type":"parametric"},"value":"-5"}}},{"name":"line_1","shape":{"@attributes":{"type":"line","drawTrails":"false","drawVectors":"false"},"vectors":{"@attributes":{"yAccel":"false","Vel":"false","xAccel":"false","yVel":"false","xVel":"false","Accel":"false"}},"width":{"calculator":{"@attributes":{"type":"parametric"},"value":"20"}},"height":{"calculator":{"@attributes":{"type":"parametric"},"value":"0"}},"angle":{"calculator":{"@attributes":{"type":"parametric"},"value":"0"}},"graphOptions":{"@attributes":{"graphVisible":"false"},"initiallyOn":{"@attributes":{"yAccel":"false","yVel":"false","xAccel":"false","xVel":"false","yPos":"false","xPos":"false"}}}},"color":{"red":"153","green":"153","blue":"153"},"xpath":{"calculator":{"@attributes":{"type":"parametric"},"value":"-10"}},"ypath":{"calculator":{"@attributes":{"type":"parametric"},"value":"5"}}},{"name":"line_2","shape":{"@attributes":{"type":"line","drawTrails":"false","drawVectors":"false"},"vectors":{"@attributes":{"yAccel":"false","Vel":"false","xAccel":"false","yVel":"false","xVel":"false","Accel":"false"}},"width":{"calculator":{"@attributes":{"type":"parametric"},"value":"20"}},"height":{"calculator":{"@attributes":{"type":"parametric"},"value":"0"}},"angle":{"calculator":{"@attributes":{"type":"parametric"},"value":"0"}},"graphOptions":{"@attributes":{"graphVisible":"false"},"initiallyOn":{"@attributes":{"yAccel":"false","yVel":"false","xAccel":"false","xVel":"false","yPos":"false","xPos":"false"}}}},"color":{"red":"153","green":"153","blue":"153"},"xpath":{"calculator":{"@attributes":{"type":"parametric"},"value":"-10"}},"ypath":{"calculator":{"@attributes":{"type":"parametric"},"value":"-5"}}},{"name":"mask_right","shape":{"@attributes":{"type":"rectangle","drawTrails":"false","drawVectors":"false"},"vectors":{"@attributes":{"yAccel":"false","Vel":"false","xAccel":"false","yVel":"false","xVel":"false","Accel":"false"}},"width":{"calculator":{"@attributes":{"type":"parametric"},"value":"12"}},"height":{"calculator":{"@attributes":{"type":"parametric"},"value":"24"}},"angle":{"calculator":{"@attributes":{"type":"parametric"},"value":"0"}},"graphOptions":{"@attributes":{"graphVisible":"false"},"initiallyOn":{"@attributes":{"yAccel":"false","yVel":"false","xAccel":"false","xVel":"false","yPos":"false","xPos":"false"}}}},"color":{"red":"153","green":"153","blue":"153"},"xpath":{"calculator":{"@attributes":{"type":"parametric"},"value":"6"}},"ypath":{"calculator":{"@attributes":{"type":"parametric"},"value":"0"}}}],"object":[{"@attributes":{"class":"edu.ncssm.iwp.objects.grapher.DObject_Grapher"},"name":"closed","equation":"1.8*cos(6.28*x\/40)*cos(6.28*1*y)","boxX":"0.0","boxY":"5.0","boxW":"20.0","boxH":"4.0","res":"100","stroke":"2","showBounding":"true","transformCoords":"true","color":{"red":"0","green":"0","blue":"255"}},{"@attributes":{"class":"edu.ncssm.iwp.objects.grapher.DObject_Grapher"},"name":"open","equation":"1.8*cos(6.28*2*x\/40)*cos(6.28*2*y)","boxX":"0.0","boxY":"-5.0","boxW":"20.0","boxH":"4.0","res":"100","stroke":"2","showBounding":"true","transformCoords":"true","color":{"red":"0","green":"0","blue":"255"}},{"@attributes":{"class":"edu.ncssm.iwp.objects.floatingtext.DObject_FloatingText"},"name":"closed_pipe","text":"Closed Pipe","units":{},"value":{"calculator":{"@attributes":{"type":"parametric"},"value":"0"}},"fontSize":"20","showValue":"false","color":{"red":"255","green":"255","blue":"0"},"ypath":{"calculator":{"@attributes":{"type":"parametric"},"value":"8"}},"xpath":{"calculator":{"@attributes":{"type":"parametric"},"value":"-6.5"}}},{"@attributes":{"class":"edu.ncssm.iwp.objects.floatingtext.DObject_FloatingText"},"name":"open_pipe","text":"Open Pipe","units":{},"value":{"calculator":{"@attributes":{"type":"parametric"},"value":"0"}},"fontSize":"20","showValue":"false","color":{"red":"255","green":"255","blue":"0"},"ypath":{"calculator":{"@attributes":{"type":"parametric"},"value":"-2.3"}},"xpath":{"calculator":{"@attributes":{"type":"parametric"},"value":"-6.3"}}}]}}